LICENSE
MANIFEST.in
README.md
requirements.txt
setup.cfg
setup.py
thegamesdb/__init__.py
thegamesdb/api.py
thegamesdb/base.py
thegamesdb/item.py
thegamesdb/items.py
thegamesdb/resources.py
thegamesdb.egg-info/PKG-INFO
thegamesdb.egg-info/SOURCES.txt
thegamesdb.egg-info/dependency_links.txt
thegamesdb.egg-info/top_level.txt
thegamesdb/test/__init__.py
thegamesdb/test/mockdb.py
thegamesdb/test/tests.py