Metadata-Version: 1.1
Name: thegamesdb
Version: 0.3
Summary: The Games DB API wrapper for Python
Home-page: https://github.com/rogerhil/thegamesdb
Author: Rogerio Hilbert Lima
Author-email: rogerhil@gmail.com
License: UNKNOWN
Download-URL: https://github.com/rogerhil/thegamesdb/tarball/0.3
Platform: UNKNOWN
